izitest/__init__.py
izitest/betterprint.py
izitest/checks.py
izitest/path.py
izitest/py.typed
izitest/test.py
izitest/testcase.py
izitest/testfile.py
izitest/testsuite.py
izitest/jinja2/bootstrap.min.css
izitest/jinja2/bootstrap.min.js
izitest/jinja2/jquery-3.4.1.slim.min.js
izitest/jinja2/popper.min.js
izitest/jinja2/report.html.j2
izitest-2.0.4.dist-info/LICENSE
izitest-2.0.4.dist-info/METADATA
izitest-2.0.4.dist-info/WHEEL
izitest-2.0.4.dist-info/top_level.txt
izitest-2.0.4.dist-info/RECORD
