Metadata-Version: 2.1
Name: izitest
Version: 2.0.4
Summary: An easy test suite
Home-page: https://izitest.rtfd.io
Author: Kenji 'Nhqml' Gaillac
Author-email: kenji.gaillac@epita.fr
License: GNU GPLv3
Project-URL: Source, https://github.com/nhqml/izitest
Project-URL: Documentation, https://izitest.rtfd.io
Platform: Any
Classifier: Development Status :: 3 - Alpha
Classifier: Intended Audience :: Developers
Classifier: Programming Language :: Python :: 3
Classifier: License :: OSI Approved :: GNU General Public License v3 (GPLv3)
Classifier: Operating System :: OS Independent
Requires-Python: >=3.6
Requires-Dist: PyYAML (>=5.3)
Requires-Dist: termcolor (>=1.1.0)
Requires-Dist: Jinja2 (>=2.11.1)
